dyco/.idea/inspectionProfiles/Project_Default.xml
dyco/.idea/LagRemover_INDEV.iml
dyco/.idea/misc.xml
dyco/.idea/modules.xml
dyco/.idea/vcs.xml
dyco/.idea/workspace.xml
dyco/__init__.py
dyco/analyze.py
dyco/cli.py
dyco/correction.py
dyco/dyco.py
dyco/files.py
dyco/lag.py
dyco/loop.py
dyco/plot.py
dyco/setup.py
dyco-2.0.3.dist-info/LICENSE
dyco-2.0.3.dist-info/METADATA
dyco-2.0.3.dist-info/WHEEL
dyco-2.0.3.dist-info/RECORD
