Metadata-Version: 2.3
Name: dyco
Version: 2.0.3
Summary: Dynamic lag compensation
Author: Lukas Hörtnagl
Author-email: lukas.hoertnagl@usys.ethz.ch
Requires-Python: >=3.11,<3.12
Classifier: Programming Language :: Python :: 3
Classifier: Programming Language :: Python :: 3.11
Requires-Dist: diive (>=0.86.0)
Requires-Dist: matplotlib (>=3.8.3)
Requires-Dist: pandas (>=2.2.3,<3.0.0)
Requires-Dist: scipy (>=1.12.0)
